re_technical_report/__init__.py
re_technical_report/data_analysis_helper_fun.py
re_technical_report/model_variations.py
re_technical_report-0.0.11a1.dist-info/LICENSE
re_technical_report-0.0.11a1.dist-info/METADATA
re_technical_report-0.0.11a1.dist-info/WHEEL
re_technical_report-0.0.11a1.dist-info/top_level.txt
re_technical_report-0.0.11a1.dist-info/RECORD
