Metadata-Version: 2.1
Name: re-technical-report
Version: 0.0.11a1
Summary: Helper functions for the report 'Assessing a Formal Model of Reflective Equilibrium'
Home-page: https://github.com/re-models/re-technical-report
Author: Sebastian Cacean, Andreas Freivogel
Author-email: sebastian.cacean@kit.edu, andreas.freivogel@unibe.ch
Classifier: Programming Language :: Python :: 3.9
Classifier: License :: OSI Approved :: MIT License
Classifier: Operating System :: OS Independent
Requires-Python: >=3.9
License-File: LICENSE
Requires-Dist: rethon
Requires-Dist: matplotlib-venn
Requires-Dist: seaborn
